aping.py
setup.py
aping.egg-info/PKG-INFO
aping.egg-info/SOURCES.txt
aping.egg-info/dependency_links.txt
aping.egg-info/entry_points.txt
aping.egg-info/requires.txt
aping.egg-info/top_level.txt