Metadata-Version: 1.0
Name: aping
Version: 0.1.0.dev0
Summary: Audio ping
Home-page: https://github.com/zakhar/aping
Author: Zakhar Zibarov
Author-email: zakhar.zibarov@gmail.com
License: GPLv3
Platform: UNKNOWN
